serialdispatch/__init__.py
serialdispatch/__main__.py
serialdispatch/frame.py
serialdispatch/sdispatch.py
serialdispatch/sdisplot.py
serialdispatch/version.py
serialdispatch-0.2.0.dist-info/DESCRIPTION.rst
serialdispatch-0.2.0.dist-info/METADATA
serialdispatch-0.2.0.dist-info/RECORD
serialdispatch-0.2.0.dist-info/WHEEL
serialdispatch-0.2.0.dist-info/entry_points.txt
serialdispatch-0.2.0.dist-info/metadata.json
serialdispatch-0.2.0.dist-info/top_level.txt
