Metadata-Version: 2.0
Name: serialdispatch
Version: 0.2.0
Summary: Easy serial communication using Dispatch
Home-page: https://github.com/slightlynybbled/SerialDispatch
Author: Jason R. Jones
Author-email: slightlynybbled@gmail.com
License: MIT
Platform: UNKNOWN
Classifier: Development Status :: 3 - Alpha
Classifier: Intended Audience :: Developers
Classifier: Natural Language :: English
Classifier: Topic :: System :: Hardware
Classifier: Topic :: System :: Monitoring
Classifier: Programming Language :: Python :: 3
Classifier: Programming Language :: Python :: 3 :: Only
Classifier: Programming Language :: Python :: 3.1
Classifier: Programming Language :: Python :: 3.2
Classifier: Programming Language :: Python :: 3.3
Classifier: Programming Language :: Python :: 3.4
Classifier: Programming Language :: Python :: 3.5
Requires-Dist: click (>=6.7)
Requires-Dist: matplotlib (>=2.0.2)
Requires-Dist: pyserial (>=3.4)
